py_gdelt/__init__.py
py_gdelt/cache.py
py_gdelt/client.py
py_gdelt/config.py
py_gdelt/endpoints/__init__.py
py_gdelt/endpoints/base.py
py_gdelt/endpoints/context.py
py_gdelt/endpoints/doc.py
py_gdelt/endpoints/events.py
py_gdelt/endpoints/geo.py
py_gdelt/endpoints/gkg.py
py_gdelt/endpoints/gkg_geojson.py
py_gdelt/endpoints/graphs.py
py_gdelt/endpoints/lowerthird.py
py_gdelt/endpoints/mentions.py
py_gdelt/endpoints/ngrams.py
py_gdelt/endpoints/radio_ngrams.py
py_gdelt/endpoints/tv.py
py_gdelt/endpoints/tv_gkg.py
py_gdelt/endpoints/tv_ngrams.py
py_gdelt/endpoints/tvv.py
py_gdelt/endpoints/vgkg.py
py_gdelt/exceptions.py
py_gdelt/filters.py
py_gdelt/lookups/__init__.py
py_gdelt/lookups/_base_tag_lookup.py
py_gdelt/lookups/_utils.py
py_gdelt/lookups/cameo.py
py_gdelt/lookups/countries.py
py_gdelt/lookups/data/cameo_codes.json
py_gdelt/lookups/data/cameo_goldstein.json
py_gdelt/lookups/data/countries.json
py_gdelt/lookups/data/gcam_codebook.json
py_gdelt/lookups/data/gkg_themes.json
py_gdelt/lookups/data/image_tags.json
py_gdelt/lookups/data/image_web_tags.json
py_gdelt/lookups/data/languages.json
py_gdelt/lookups/gcam.py
py_gdelt/lookups/image_tags.py
py_gdelt/lookups/image_web_tags.py
py_gdelt/lookups/languages.py
py_gdelt/lookups/models.py
py_gdelt/lookups/themes.py
py_gdelt/mcp_server/README.md
py_gdelt/mcp_server/__init__.py
py_gdelt/mcp_server/example_usage.py
py_gdelt/mcp_server/server.py
py_gdelt/models/__init__.py
py_gdelt/models/_internal.py
py_gdelt/models/articles.py
py_gdelt/models/common.py
py_gdelt/models/events.py
py_gdelt/models/gkg.py
py_gdelt/models/graphs.py
py_gdelt/models/ngrams.py
py_gdelt/models/vgkg.py
py_gdelt/parsers/__init__.py
py_gdelt/parsers/broadcast_ngrams.py
py_gdelt/parsers/events.py
py_gdelt/parsers/gkg.py
py_gdelt/parsers/graphs.py
py_gdelt/parsers/mentions.py
py_gdelt/parsers/ngrams.py
py_gdelt/parsers/vgkg.py
py_gdelt/py.typed
py_gdelt/sources/QUICK_REFERENCE.md
py_gdelt/sources/README.md
py_gdelt/sources/__init__.py
gdelt_py-0.1.6.dist-info/WHEEL
gdelt_py-0.1.6.dist-info/METADATA
gdelt_py-0.1.6.dist-info/RECORD
