Metadata-Version: 2.3
Name: gdelt-py
Version: 0.1.6
Summary: Python client library for GDELT (Global Database of Events, Language, and Tone)
Keywords: gdelt,news,events,data-science,api
Author: Robert Wasilewski
Author-email: Robert Wasilewski <wasilewski.robert@gmail.com>
Classifier: Development Status :: 3 - Alpha
Classifier: Intended Audience :: Developers
Classifier: Intended Audience :: Science/Research
Classifier: License :: OSI Approved :: MIT License
Classifier: Programming Language :: Python :: 3.11
Classifier: Programming Language :: Python :: 3.12
Classifier: Programming Language :: Python :: 3.13
Classifier: Programming Language :: Python :: 3.14
Classifier: Topic :: Scientific/Engineering :: Information Analysis
Requires-Dist: httpx>=0.28.1
Requires-Dist: pydantic>=2.12.5
Requires-Dist: pydantic-settings>=2.12.0
Requires-Dist: tenacity>=9.1.2
Requires-Dist: tqdm>=4.67.1
Requires-Dist: defusedxml>=0.7.1
Requires-Dist: anyio>=4.0
Requires-Dist: urllib3>=2.6.3
Requires-Dist: google-cloud-bigquery>=3.0 ; extra == 'bigquery'
Requires-Dist: commitizen>=3.0 ; extra == 'dev'
Requires-Dist: geonamescache>=2.0 ; extra == 'dev'
Requires-Dist: interrogate>=1.7.0 ; extra == 'dev'
Requires-Dist: memray>=1.19.1 ; extra == 'dev'
Requires-Dist: mypy>=1.0 ; extra == 'dev'
Requires-Dist: pip-audit>=2.0 ; extra == 'dev'
Requires-Dist: pre-commit>=3.5.0 ; extra == 'dev'
Requires-Dist: pydoclint>=0.5.0 ; extra == 'dev'
Requires-Dist: pyright>=1.1.408 ; extra == 'dev'
Requires-Dist: pytest>=8.0 ; extra == 'dev'
Requires-Dist: pytest-asyncio>=0.23 ; extra == 'dev'
Requires-Dist: pytest-cov>=4.0 ; extra == 'dev'
Requires-Dist: pytest-timeout>=2.0 ; extra == 'dev'
Requires-Dist: respx>=0.21 ; extra == 'dev'
Requires-Dist: ruff>=0.8 ; extra == 'dev'
Requires-Dist: mkdocs>=1.5 ; extra == 'docs'
Requires-Dist: mkdocs-material>=9.0 ; extra == 'docs'
Requires-Dist: mkdocstrings[python]>=0.24 ; extra == 'docs'
Requires-Dist: mkdocs-llmstxt>=0.2.0 ; extra == 'docs'
Requires-Dist: mcp>=1.0 ; extra == 'mcp'
Requires-Dist: pandas>=2.0 ; extra == 'pandas'
Requires-Python: >=3.11
Project-URL: Homepage, https://github.com/RBozydar/py-gdelt
Project-URL: Documentation, https://github.com/RBozydar/py-gdelt#readme
Project-URL: Repository, https://github.com/RBozydar/py-gdelt
Project-URL: Issues, https://github.com/RBozydar/py-gdelt/issues
Provides-Extra: bigquery
Provides-Extra: dev
Provides-Extra: docs
Provides-Extra: mcp
Provides-Extra: pandas
